Workbook
Name AnnualExpenses: Summary!$F$3
Name AnnualProfit: Summary!$F$4
Name AnnualRevenue: Summary!$F$2

Sheet Revenue Analysis
A1: Customer Type | B1: Customer Name | C1: Order Amount | D1: Product Category | E1: Quarter | F1: Region | G1: Discount Rate | H1: Discount Amount | I1: Final Order Amount | J1: Shipping Charge | K1: Final Total
A2: Premium | B2: Acme Industries | C2: 12500 | D2: Cloud Security | E2: Q1 | F2: North America | G2: =IF(A2="Premium",0.15,0.05) -> 0.15 | H2: =C2*G2 -> 1875 | I2: =C2-H2 -> 10625 | J2: =IF(I2>=10000,0,IF(I2>=5000,50,100)) -> 0 | K2: =I2+J2 -> 10625
A3: Standard | B3: Blue Ridge Co | C3: 4200 | D3: Mobile Platform | E3: Q1 | F3: Latin America | G3: =IF(A3="Premium",0.15,0.05) -> 0.05 | H3: =C3*G3 -> 210 | I3: =C3-H3 -> 3990 | J3: =IF(I3>=10000,0,IF(I3>=5000,50,100)) -> 100 | K3: =I3+J3 -> 4090
A4: Premium | B4: Crestview Ltd | C4: 8900 | D4: AI Analytics | E4: Q1 | F4: Europe | G4: =IF(A4="Premium",0.15,0.05) -> 0.15 | H4: =C4*G4 -> 1335 | I4: =C4-H4 -> 7565 | J4: =IF(I4>=10000,0,IF(I4>=5000,50,100)) -> 50 | K4: =I4+J4 -> 7615
A5: Standard | B5: Delta Systems | C5: 3100 | D5: Cloud Security | E5: Q2 | F5: Asia Pacific | G5: =IF(A5="Premium",0.15,0.05) -> 0.05 | H5: =C5*G5 -> 155 | I5: =C5-H5 -> 2945 | J5: =IF(I5>=10000,0,IF(I5>=5000,50,100)) -> 100 | K5: =I5+J5 -> 3045
A6: Premium | B6: Eastgate Corp | C6: 15200 | D6: Mobile Platform | E6: Q2 | F6: North America | G6: =IF(A6="Premium",0.15,0.05) -> 0.15 | H6: =C6*G6 -> 2280 | I6: =C6-H6 -> 12920 | J6: =IF(I6>=10000,0,IF(I6>=5000,50,100)) -> 0 | K6: =I6+J6 -> 12920
A7: Standard | B7: Falcon Group | C7: 2800 | D7: AI Analytics | E7: Q2 | F7: Latin America | G7: =IF(A7="Premium",0.15,0.05) -> 0.05 | H7: =C7*G7 -> 140 | I7: =C7-H7 -> 2660 | J7: =IF(I7>=10000,0,IF(I7>=5000,50,100)) -> 100 | K7: =I7+J7 -> 2760
A8: Premium | B8: Global Tech | C8: 11400 | D8: Cloud Security | E8: Q3 | F8: Europe | G8: =IF(A8="Premium",0.15,0.05) -> 0.15 | H8: =C8*G8 -> 1710 | I8: =C8-H8 -> 9690 | J8: =IF(I8>=10000,0,IF(I8>=5000,50,100)) -> 50 | K8: =I8+J8 -> 9740
A9: Standard | B9: Harbor View | C9: 4900 | D9: Mobile Platform | E9: Q3 | F9: Asia Pacific | G9: =IF(A9="Premium",0.15,0.05) -> 0.05 | H9: =C9*G9 -> 245 | I9: =C9-H9 -> 4655 | J9: =IF(I9>=10000,0,IF(I9>=5000,50,100)) -> 100 | K9: =I9+J9 -> 4755
A10: Premium | B10: Ironside Inc | C10: 9800 | D10: AI Analytics | E10: Q3 | F10: North America | G10: =IF(A10="Premium",0.15,0.05) -> 0.15 | H10: =C10*G10 -> 1470 | I10: =C10-H10 -> 8330 | J10: =IF(I10>=10000,0,IF(I10>=5000,50,100)) -> 50 | K10: =I10+J10 -> 8380
A11: Standard | B11: Jetstream Co | C11: 3600 | D11: Cloud Security | E11: Q4 | F11: Latin America | G11: =IF(A11="Premium",0.15,0.05) -> 0.05 | H11: =C11*G11 -> 180 | I11: =C11-H11 -> 3420 | J11: =IF(I11>=10000,0,IF(I11>=5000,50,100)) -> 100 | K11: =I11+J11 -> 3520
A12: Premium | B12: Keystone Ltd | C12: 13700 | D12: Mobile Platform | E12: Q4 | F12: Europe | G12: =IF(A12="Premium",0.15,0.05) -> 0.15 | H12: =C12*G12 -> 2055 | I12: =C12-H12 -> 11645 | J12: =IF(I12>=10000,0,IF(I12>=5000,50,100)) -> 0 | K12: =I12+J12 -> 11645
A13: Standard | B13: Lakeside Corp | C13: 2400 | D13: AI Analytics | E13: Q4 | F13: Asia Pacific | G13: =IF(A13="Premium",0.15,0.05) -> 0.05 | H13: =C13*G13 -> 120 | I13: =C13-H13 -> 2280 | J13: =IF(I13>=10000,0,IF(I13>=5000,50,100)) -> 100 | K13: =I13+J13 -> 2380
... A23: Standard | B23: Vertex Ltd | C23: 3800 | D23: Cloud Security | E23: Q1 | F23: Latin America | G23: =IF(A23="Premium",0.15,0.05) -> 0.05 | H23: =C23*G23 -> 190 | I23: =C23-H23 -> 3610 | J23: =IF(I23>=10000,0,IF(I23>=5000,50,100)) -> 100 | K23: =I23+J23 -> 3710

Sheet Revenue
A1: Month | B1: Cloud Security | C1: Mobile Platform | D1: AI Analytics | E1: Integration Suite | F1: Customer Portal | G1: Total Revenue
A2: January | B2: 38500 | C2: 24200 | D2: 19800 | E2: 12400 | F2: 8900 | G2: 103800
A3: February | B3: 41200 | C3: 25800 | D3: 21400 | E3: 13100 | F3: 9400 | G3: 110900
A4: March | B4: 39800 | C4: 23900 | D4: 20600 | E4: 12800 | F4: 9100 | G4: 106200
A5: Q1 Total | B5: 119500 | C5: 73900 | D5: 61800 | E5: 38300 | F5: 27400 | G5: 320900
A6: April | B6: 43500 | C6: 27200 | D6: 22800 | E6: 14200 | F6: 10100 | G6: 117800
A7: May | B7: 45800 | C7: 28900 | D7: 24100 | E7: 15000 | F7: 10700 | G7: 124500
A8: June | B8: 42600 | C8: 26800 | D8: 23200 | E8: 14500 | F8: 10300 | G8: 117400
A9: Q2 Total | B9: 131900 | C9: 82900 | D9: 70100 | E9: 43700 | F9: 31100 | G9: 359700
A10: July | B10: 47200 | C10: 30100 | D10: 25400 | E10: 15800 | F10: 11200 | G10: 129700
A11: August | B11: 49500 | C11: 31800 | D11: 26900 | E11: 16600 | F11: 11800 | G11: 136600
A12: September | B12: 46800 | C12: 29600 | D12: 25100 | E12: 15500 | F12: 11000 | G12: 128000
A13: Q3 Total | B13: 143500 | C13: 91500 | D13: 77400 | E13: 47900 | F13: 34000 | G13: 394300
... A17: Q4 Total | B17: 155400 | C17: 100900 | D17: 85800 | E17: 52700 | F17: 37400 | G17: 432200

Sheet Expenses
A1: Month | B1: Staff and Salaries | C1: Technology | D1: Marketing | E1: Operations | F1: Support | G1: Total Expenses
A2: January | B2: 42000 | C2: 8500 | D2: 6200 | E2: 4800 | F2: 3100 | G2: 64600
A3: February | B3: 42000 | C3: 8800 | D3: 6500 | E3: 4900 | F3: 3200 | G3: 65400
A4: March | B4: 42000 | C4: 9100 | D4: 6800 | E4: 5000 | F4: 3300 | G4: 66200
A5: Q1 Total | B5: 126000 | C5: 26400 | D5: 19500 | E5: 14700 | F5: 9600 | G5: 196200
A6: April | B6: 44000 | C6: 9400 | D6: 7100 | E6: 5200 | F6: 3400 | G6: 69100
A7: May | B7: 44000 | C7: 9700 | D7: 7400 | E7: 5300 | F7: 3500 | G7: 69900
A8: June | B8: 44000 | C8: 10000 | D8: 7700 | E8: 5400 | F8: 3600 | G8: 70700
A9: Q2 Total | B9: 132000 | C9: 29100 | D9: 22200 | E9: 15900 | F9: 10500 | G9: 209700
A10: July | B10: 46000 | C10: 10300 | D10: 8000 | E10: 5600 | F10: 3700 | G10: 73600
A11: August | B11: 46000 | C11: 10600 | D11: 8300 | E11: 5700 | F11: 3800 | G11: 74400
A12: September | B12: 46000 | C12: 10900 | D12: 8600 | E12: 5800 | F12: 3900 | G12: 75200
A13: Q3 Total | B13: 138000 | C13: 31800 | D13: 24900 | E13: 17100 | F13: 11400 | G13: 223200
... A17: Q4 Total | B17: 144000 | C17: 34500 | D17: 27600 | E17: 18300 | F17: 12300 | G17: 236700

Sheet Sales Data
A1: Product | B1: Units Sold | C1: Unit Price | D1: Revenue | E1: Profit
A2: Cloud Security | B2: 145 | C2: 299 | D2: 43355 | E2: 18200
A3: Mobile Platform | B3: 98 | C3: 199 | D3: 19502 | E3: 7800
A4: AI Analytics | B4: 112 | C4: 349 | D4: 39088 | E4: 16500
A5: Integration Suite | B5: 67 | C5: 249 | D5: 16683 | E5: 6200
A6: Customer Portal | B6: 89 | C6: 179 | D6: 15931 | E6: 5800
A7: Cloud Security Pro | B7: 54 | C7: 499 | D7: 26946 | E7: 12100
A8: Mobile Platform Plus | B8: 76 | C8: 299 | D8: 22724 | E8: 9400
A9: AI Analytics Basic | B9: 134 | C9: 149 | D9: 19966 | E9: 7200
A10: Integration Suite Pro | B10: 45 | C10: 399 | D10: 17955 | E10: 8100
A11: Customer Portal Plus | B11: 62 | C11: 249 | D11: 15438 | E11: 6300
A12: Cloud Security Lite | B12: 88 | C12: 199 | D12: 17512 | E12: 6800
A13: Mobile Platform Basic | B13: 103 | C13: 149 | D13: 15347 | E13: 5400
... A16: Customer Portal Basic | B16: 94 | C16: 129 | D16: 12126 | E16: 4100
A17: Total | B17: =SUM(B2:B16) -> 1294 | C17: =AVERAGE(C2:C16) -> 266.33333 | D17: =SUM(D2:D16) -> 325596 | E17: =SUM(E2:E16) -> 132000

Sheet Summary
A1: Category | B1: Q1 Total | C1: Q2 Total | D1: Q3 Total | E1: Q4 Total | F1: Annual Total
A2: Revenue | B2: =Revenue!G5 -> 320900 | C2: =Revenue!G9 -> 359700 | D2: =Revenue!G13 -> 394300 | E2: =Revenue!G17 -> 432200 | F2: =B2+C2+D2+E2 -> 1507100
A3: Expenses | B3: =Expenses!G5 -> 196200 | C3: =Expenses!G9 -> 209700 | D3: =Expenses!G13 -> 223200 | E3: =Expenses!G17 -> 236700 | F3: =B3+C3+D3+E3 -> 865800
A4: Profit | B4: =B2-B3 -> 124700 | C4: =C2-C3 -> 150000 | D4: =D2-D3 -> 171100 | E4: =E2-E3 -> 195500 | F4: =F2-F3 -> 641300
A7: Profit Margin | B7: =B4/B2 -> 0.38859458 | C7: =C4/C2 -> 0.41701418 | D7: =D4/D2 -> 0.43393355 | E7: =E4/E2 -> 0.45233688 | F7: =AnnualProfit/AnnualRevenue -> 0.42551921

Sheet Analysis Questions
B1: Analysis Questions
B3: Answer each question in 2 to 4 sentences. Use specific values from this workbook to support your answer.
B5: Question 1: IF Function Analysis (Task 1): Look at the discount amounts across all 22 orders. Do Premium customers always pay less after discount than Standard customers? Use 2 specific examples from your data to support your answer. What does this tell you about how discount rates interact with order size?
B6: Add your response here
B15: Question 2: Summary Report Analysis (Task 2): Look at the quarterly profit margins in row 7 of your Summary worksheet. Describe the trend you see across Q1 through Q4. Does Global Connect Solutions appear to be improving its profitability over the year? Use specific values to support your conclusion.
B16: Add your response here
B25: Question 3: Synthesis: Based on your IF function analysis, summary report, and sales data, write a short summary of Global Connect Solutions’ financial position. Identify one strength and one area of concern. Use at least 2 specific numbers from your workbook to support each point.
B26: Add your response here
